bucketpusher/__init__.py
bucketpusher/__version__.py
bucketpusher/app.py
bucketpusher/auth.py
bucketpusher/cli.py
bucketpusher/config.py
bucketpusher/exceptions.py
bucketpusher/layout.py
bucketpusher/uploader.py
bucketpusher/utils.py
bucketpusher-0.6.0.dist-info/entry_points.txt
bucketpusher-0.6.0.dist-info/LICENSE.txt
bucketpusher-0.6.0.dist-info/WHEEL
bucketpusher-0.6.0.dist-info/METADATA
bucketpusher-0.6.0.dist-info/RECORD
