Metadata-Version: 2.1
Name: bucketpusher
Version: 0.6.0
Summary: Push local files to cloud storage bucket
License: MIT
Author: Dominic Ward
Author-email: dom@deeuu.me
Requires-Python: >=3.7,<4.0
Classifier: License :: OSI Approved :: MIT License
Classifier: Programming Language :: Python :: 3
Classifier: Programming Language :: Python :: 3.7
Classifier: Programming Language :: Python :: 3.8
Classifier: Programming Language :: Python :: 3.9
Requires-Dist: PySimpleGUI (>=4.30.0,<5.0.0)
Requires-Dist: appdirs (>=1.4.4,<2.0.0)
Requires-Dist: click (>=7.1.2,<8.0.0)
Requires-Dist: cryptography (>=3.2.1,<4.0.0)
Requires-Dist: flake8 (>=3.8.4,<4.0.0)
Requires-Dist: google-auth-oauthlib (>=0.4.2,<0.5.0)
Requires-Dist: google-cloud-storage (>=1.32.0,<2.0.0)
Requires-Dist: google-crc32c (>=1.0.0,<2.0.0)
Requires-Dist: loguru (>=0.5.3,<0.6.0)
